Metadata-Version: 2.1
Name: django-roadies
Version: 0.1.1
Summary: Suite of django specific utilities/helpers.
Home-page: https://github.com/anthonyalmarza/django-roadies
Author: Anthony Almarza
Author-email: anthony.almarza@gmail.com
License: MIT
Keywords: django-roadies,django,roadies,utils,tests,handlers
Platform: UNKNOWN
Classifier: Development Status :: 4 - Beta
Classifier: Environment :: Console
Classifier: Intended Audience :: Developers
Classifier: Intended Audience :: Information Technology
Classifier: License :: OSI Approved :: MIT License
Classifier: Operating System :: OS Independent
Classifier: Programming Language :: Python
